wechat_mcp/__init__.py
wechat_mcp/__main__.py
wechat_mcp/server.py
wechat_mcp-0.1.11.dist-info/METADATA
wechat_mcp-0.1.11.dist-info/WHEEL
wechat_mcp-0.1.11.dist-info/entry_points.txt
wechat_mcp-0.1.11.dist-info/top_level.txt
wechat_mcp-0.1.11.dist-info/RECORD
