Metadata-Version: 2.4
Name: wechat-mcp
Version: 0.1.11
Summary: 微信mcp服务,实现消息收发
Author-email: noah <781172480@qq.com>
Keywords: mcp,mcp server,tool calling,function calling
Requires-Python: >=3.10
Requires-Dist: httpx>=0.28.1
Requires-Dist: mcp[cli]>=1.5.0
Requires-Dist: pywxdump>=3.1.45
Requires-Dist: wxauto>=3.9.11.17.5
Provides-Extra: dev
Requires-Dist: cython; extra == "dev"
